korpy/__init__.py
korpy/core.py
korpy/games.py
korpy/holiday.py
korpy/korpyinfo.py
korpy/typofix.py
korpy/experimental/__init__.py
korpy/experimental/core.py
korpy-1.1.6.dist-info/licenses/LICENCE
korpy-1.1.6.dist-info/METADATA
korpy-1.1.6.dist-info/WHEEL
korpy-1.1.6.dist-info/top_level.txt
korpy-1.1.6.dist-info/RECORD
