Metadata-Version: 2.4
Name: korpy
Version: 1.1.6
Summary: A handy toolkit for korean texts
Home-page: https://github.com/MatthewKim12/korpy
Author: MatthewKim
Author-email: kimdjn12@gmail.com
Project-URL: Bug Tracker, https://github.com/MatthewKim12/korpy/issues
Project-URL: Changelog, https://github.com/MatthewKim12/korpy/blob/main/HISTORY.rst
Project-URL: Source Code, https://github.com/MatthewKim12/korpy/tree/main/korpy
Classifier: Programming Language :: Python :: 3
Classifier: License :: OSI Approved :: MIT License
Classifier: Operating System :: OS Independent
Requires-Python: >=3.10
License-File: LICENCE
Requires-Dist: deep-translator
Requires-Dist: holidayskr
Requires-Dist: requests
Dynamic: license-file
